swarmauri_tool_jupyterexecutenotebookwithparameters/JupyterExecuteNotebookWithParametersTool.py
swarmauri_tool_jupyterexecutenotebookwithparameters/__init__.py
swarmauri_tool_jupyterexecutenotebookwithparameters-1.1.5.dist-info/LICENSE
swarmauri_tool_jupyterexecutenotebookwithparameters-1.1.5.dist-info/METADATA
swarmauri_tool_jupyterexecutenotebookwithparameters-1.1.5.dist-info/WHEEL
swarmauri_tool_jupyterexecutenotebookwithparameters-1.1.5.dist-info/entry_points.txt
swarmauri_tool_jupyterexecutenotebookwithparameters-1.1.5.dist-info/RECORD
