Metadata-Version: 2.3
Name: swarmauri_tool_jupyterexecutenotebookwithparameters
Version: 1.1.5
Summary: A tool designed to execute parameterized notebooks using papermill, allowing dynamic input and output capture for automated workflows.
License: Apache-2.0
Author: Swarmauri Contributors
Author-email: contributors@swarmauri.com
Requires-Python: >=3.10,<3.13
Classifier: License :: OSI Approved :: Apache Software License
Classifier: Programming Language :: Python :: 3.10
Classifier: Programming Language :: Python :: 3.11
Classifier: Programming Language :: Python :: 3.12
Classifier: Programming Language :: Python :: 3.13
Requires-Dist: papermill (>=2.6.0)
Requires-Dist: swarmauri_base
Requires-Dist: swarmauri_core
Requires-Dist: swarmauri_standard
